MANIFEST.in
setup.py
covertutils/__init__.py
covertutils/exceptions.py
covertutils/helpers.py
covertutils.egg-info/PKG-INFO
covertutils.egg-info/SOURCES.txt
covertutils.egg-info/dependency_links.txt
covertutils.egg-info/top_level.txt
covertutils/bridges/__init__.py
covertutils/bridges/simplebridge.py
covertutils/crypto/__init__.py
covertutils/crypto/algorithms/__init__.py
covertutils/crypto/algorithms/__main__.py
covertutils/crypto/algorithms/crc32cyclingalgorithm.py
covertutils/crypto/algorithms/cyclingalgorithm.py
covertutils/crypto/algorithms/nullcyclingalgorithm.py
covertutils/crypto/algorithms/standardcyclingalgorithm.py
covertutils/crypto/keys/__init__.py
covertutils/crypto/keys/__main__.py
covertutils/crypto/keys/cyclingkey.py
covertutils/crypto/keys/encryptionkey.py
covertutils/crypto/keys/standardcyclingkey.py
covertutils/datamanipulation/__init__.py
covertutils/datamanipulation/adhocchunker.py
covertutils/datamanipulation/chunker.py
covertutils/datamanipulation/compressor.py
covertutils/datamanipulation/datatransformer.py
covertutils/datamanipulation/stegoinjector.py
covertutils/handlers/__init__.py
covertutils/handlers/basehandler.py
covertutils/handlers/buffering.py
covertutils/handlers/dateable.py
covertutils/handlers/functiondict.py
covertutils/handlers/interrogating.py
covertutils/handlers/resettable.py
covertutils/handlers/responseonly.py
covertutils/handlers/stageable.py
covertutils/handlers/impl/__init__.py
covertutils/handlers/impl/extendableshell.py
covertutils/handlers/impl/simpleshell.py
covertutils/handlers/impl/standardshell.py
covertutils/handlers/multi/__init__.py
covertutils/handlers/multi/multihandler.py
covertutils/orchestration/__init__.py
covertutils/orchestration/orchestrator.py
covertutils/orchestration/simpleorchestrator.py
covertutils/orchestration/stegoorchestrator.py
covertutils/orchestration/streamidentifier.py
covertutils/payloads/__init__.py
covertutils/payloads/generic/__init__.py
covertutils/payloads/generic/control.py
covertutils/payloads/generic/echo.py
covertutils/payloads/generic/example.py
covertutils/payloads/generic/file.py
