Metadata-Version: 1.0
Name: covertutils
Version: 0.3.4
Summary: Module for backdoor design and implementation.
Home-page: https://github.com/operatorequals/covertutils
Author: John Torakis - operatorequals
Author-email: john.torakis@gmail.com
License: MIT
Keywords: crypto,covert,backdoor,shell
Platform: UNKNOWN
